data/__init__.py
data/date.py
data/day.py
data/meal.py
data/menu.py
data/price.py
meylenplan-1.2.1.data/scripts/meylenplan
utils/__init__.py
utils/config.py
utils/config.yml
utils/exceptions.py
utils/menuConverter.py
utils/menuDownloader.py
utils/menuLinkScraper.py
utils/menuParser.py
utils/menuPrinter.py
utils/notificationSender.py
meylenplan-1.2.1.dist-info/LICENSE
meylenplan-1.2.1.dist-info/METADATA
meylenplan-1.2.1.dist-info/WHEEL
meylenplan-1.2.1.dist-info/top_level.txt
meylenplan-1.2.1.dist-info/RECORD
