Metadata-Version: 2.1
Name: meylenplan
Version: 1.2.1
Summary: Fetches and displays the SchlemmerMeyle meal plan for today.
Home-page: https://gitlab.com/ploth/meylenplan
Author: Felix Wege <felix.wege@tuhh.de>, Jonas Winter, Pascal Loth <pascal.loth@tuhh.de>
Author-email: pascal.loth@tuhh.de
License: GPLv3
Platform: UNKNOWN
Requires-Dist: beautifulsoup4 (>=4.5.1)
Requires-Dist: lxml (>=4.2.5)
Requires-Dist: tabulate (>=0.8.1)
Requires-Dist: urllib3 (>=1.22)
Requires-Dist: PyYAML (>=3.13)
